{"cameraMode":{"drawMode":0,"name":"Shaded","section":"Shading Mode"},"sceneLighting":true,"audioPlay":false,"sceneViewState":{"m_AlwaysRefresh":false,"showFog":true,"showSkybox":true,"showFlares":true,"showImageEffects":true,"showParticleSystems":true,"showVisualEffectGraphs":true,"m_FxEnabled":true},"in2DMode":false,"pivot":{"x":0.0,"y":0.0,"z":90.0},"rotation":{"x":-0.09466657042503357,"y":0.0050744060426950459,"z":-0.0004825855721719563,"w":-0.9954984188079834},"size":4.642552852630615,"orthographic":false}